docmat/__init__.py
docmat/__main__.py
docmat/docstring_formats/google/__init__.py
docmat/docstring_formats/google/docstring.py
docmat/docstring_formats/shared/__init__.py
docmat/docstring_formats/shared/base.py
docmat/docstring_formats/shared/elements.py
docmat/docstring_formats/shared/string_utils.py
docmat/file.py
docmat-0.1.0a1.dist-info/entry_points.txt
docmat-0.1.0a1.dist-info/WHEEL
docmat-0.1.0a1.dist-info/METADATA
docmat-0.1.0a1.dist-info/RECORD
