Metadata-Version: 2.1
Name: docmat
Version: 0.1.0a1
Summary: Python docstring formatter
License: MIT
Author: Claudio Salvatore Arcidiacono
Requires-Python: >=3.7,<4.0
Classifier: License :: OSI Approved :: MIT License
Classifier: Programming Language :: Python :: 3
Classifier: Programming Language :: Python :: 3.10
Classifier: Programming Language :: Python :: 3.7
Classifier: Programming Language :: Python :: 3.8
Classifier: Programming Language :: Python :: 3.9
